penney/__init__.py
penney/__main__.py
penney/functions.py
penney/params.py
penney-0.5.dist-info/licenses/AUTHORS.md
penney-0.5.dist-info/licenses/LICENSE
penney-0.5.dist-info/METADATA
penney-0.5.dist-info/WHEEL
penney-0.5.dist-info/entry_points.txt
penney-0.5.dist-info/top_level.txt
penney-0.5.dist-info/RECORD
