Metadata-Version: 2.4
Name: penney
Version: 0.5
Summary: Penney's game
Home-page: https://github.com/sepandhaghighi/penney
Author: Sepand Haghighi
Author-email: me@sepand.tech
License: MIT
Project-URL: Source, https://github.com/sepandhaghighi/penney
Project-URL: Tracker, https://github.com/sepandhaghighi/penney/issues
Keywords: penney probability game fun terminal
Classifier: Development Status :: 5 - Production/Stable
Classifier: Intended Audience :: Developers
Classifier: Intended Audience :: Education
Classifier: Intended Audience :: End Users/Desktop
Classifier: Natural Language :: English
Classifier: License :: OSI Approved :: MIT License
Classifier: Operating System :: OS Independent
Classifier: Programming Language :: Python :: 3.7
Classifier: Programming Language :: Python :: 3.8
Classifier: Programming Language :: Python :: 3.9
Classifier: Programming Language :: Python :: 3.10
Classifier: Programming Language :: Python :: 3.11
Classifier: Programming Language :: Python :: 3.12
Classifier: Programming Language :: Python :: 3.13
Classifier: Topic :: Scientific/Engineering :: Mathematics
Classifier: Topic :: Games/Entertainment
Classifier: Topic :: Games/Entertainment :: Simulation
Classifier: Topic :: Games/Entertainment :: Turn Based Strategy
Requires-Python: >=3.7
License-File: LICENSE
License-File: AUTHORS.md
Requires-Dist: art>=1.8
Dynamic: author
Dynamic: author-email
Dynamic: classifier
Dynamic: description
Dynamic: description-content-type
Dynamic: home-page
Dynamic: keywords
Dynamic: license
Dynamic: license-file
Dynamic: project-url
Dynamic: requires-dist
Dynamic: requires-python
Dynamic: summary
